{
  "$schema": "https://json-schema.org/draft/2020-12/schema",
  "title": "GET /time-series response",
  "type": "object",
  "additionalProperties": false,
  "description": "Contract schema only. Template file; unknown values remain null or pending_confirmation.",
  "required": [
    "station",
    "start_time",
    "end_time",
    "rows"
  ],
  "properties": {
    "station": {
      "type": "string",
      "enum": [
        "Station_1",
        "Station_2",
        "Station_3"
      ]
    },
    "start_time": {
      "type": "string"
    },
    "end_time": {
      "type": "string"
    },
    "rows": {
      "type": "array",
      "items": {
        "$ref": "./sensor_1hz.schema.json"
      }
    }
  }
}
